ndpulsecount/__init__.py
ndpulsecount/pulse_counter.py
ndpulsecount/transcode.py
ndpulsecount-0.0.2.dist-info/LICENSE.txt
ndpulsecount-0.0.2.dist-info/METADATA
ndpulsecount-0.0.2.dist-info/WHEEL
ndpulsecount-0.0.2.dist-info/top_level.txt
ndpulsecount-0.0.2.dist-info/RECORD
