Metadata-Version: 2.1
Name: ndpulsecount
Version: 0.0.2
Summary: A package to interface with the Narwhal Devices Pulse Counter
Home-page: https://https://github.com/RorySpeirs/pulse-counter
Author: Rory Speirs
Author-email: rory@narwhaldevices.com
License: MIT License
